LICENSE.TXT
setup.py
Topsis_Abhay_102016081/__init__.py
Topsis_Abhay_102016081/topsis.py
Topsis_Abhay_102016081.egg-info/PKG-INFO
Topsis_Abhay_102016081.egg-info/SOURCES.txt
Topsis_Abhay_102016081.egg-info/dependency_links.txt
Topsis_Abhay_102016081.egg-info/requires.txt
Topsis_Abhay_102016081.egg-info/top_level.txt